afrikpay_pip_sdk/Account.py
afrikpay_pip_sdk/Airtime.py
afrikpay_pip_sdk/Bill.py
afrikpay_pip_sdk/Ecommerce.py
afrikpay_pip_sdk/Money.py
afrikpay_pip_sdk/__init__.py
afrikpay_pip_sdk-0.0.3.dist-info/LICENSE
afrikpay_pip_sdk-0.0.3.dist-info/METADATA
afrikpay_pip_sdk-0.0.3.dist-info/WHEEL
afrikpay_pip_sdk-0.0.3.dist-info/top_level.txt
afrikpay_pip_sdk-0.0.3.dist-info/RECORD
