Metadata-Version: 2.1
Name: afrikpay-pip-sdk
Version: 0.0.3
Summary: A library to facilitate Afrikpay api integration
Home-page: https://github.com/Georges-Ngandeu/AfrikpayPythonSdk
Author: Georges Ngandeu
Author-email: georgesngandeu@gmail.com
License: Apache License 2.0
Platform: UNKNOWN
Classifier: Programming Language :: Python :: 3
Classifier: License :: OSI Approved :: MIT License
Classifier: Operating System :: OS Independent
Requires-Dist: requests
